README.md
setup.cfg
setup.py
RestResponse/__init__.py
RestResponse/objects.py
RestResponse/utils.py
RestResponse.egg-info/PKG-INFO
RestResponse.egg-info/SOURCES.txt
RestResponse.egg-info/dependency_links.txt
RestResponse.egg-info/requires.txt
RestResponse.egg-info/top_level.txt
RestResponse/orm/__init__.py
RestResponse/orm/sqlalchemy/__init__.py