Metadata-Version: 2.1
Name: RestResponse
Version: 3.0.4
Summary: A fluent python object for interfacing with RESTful JSON APIs.
Home-page: https://github.com/tysonholub/RestResponse.git
Author: Tyson Holub
Author-email: tyson@tysonholub.com
License: MIT
Platform: UNKNOWN
